kb_trend/__init__.py
kb_trend/__main__.py
kb_trend/cli/__init__.py
kb_trend/cli/app.py
kb_trend/cli/init_cmd.py
kb_trend/cli/keywords.py
kb_trend/cli/process.py
kb_trend/cli/run.py
kb_trend/cli/status.py
kb_trend/config/__init__.py
kb_trend/config/manager.py
kb_trend/config/models.py
kb_trend/config/wizard.py
kb_trend/database/__init__.py
kb_trend/database/manager.py
kb_trend/database/schema.py
kb_trend/keywords/__init__.py
kb_trend/keywords/loader.py
kb_trend/keywords/query_builder.py
kb_trend/processor/__init__.py
kb_trend/processor/relative.py
kb_trend/scraper/__init__.py
kb_trend/scraper/client.py
kb_trend/scraper/parser.py
kb_trend/scraper/worker.py
kb_trend/utils/__init__.py
kb_trend/utils/hash.py
kb_trend-1.0.1.dist-info/METADATA
kb_trend-1.0.1.dist-info/WHEEL
kb_trend-1.0.1.dist-info/entry_points.txt
kb_trend-1.0.1.dist-info/licenses/LICENSE
kb_trend-1.0.1.dist-info/RECORD
