Metadata-Version: 2.4
Name: kb-trend
Version: 1.0.1
Summary: Swedish National Library newspaper trend scraper
Project-URL: Homepage, https://github.com/matjoha/kb-trend
Project-URL: Repository, https://github.com/matjoha/kb-trend
Author-email: Mathias Johansson <MathiasJoha@gmail.com>
License: CC BY NC
License-File: LICENSE
Keywords: kb,newspaper,scraper,swedish,trends
Classifier: Development Status :: 4 - Beta
Classifier: Intended Audience :: Science/Research
Classifier: Programming Language :: Python :: 3.11
Classifier: Programming Language :: Python :: 3.12
Classifier: Programming Language :: Python :: 3.13
Classifier: Topic :: Text Processing
Requires-Python: >=3.11
Requires-Dist: httpx>=0.25.0
Requires-Dist: loguru>=0.7.0
Requires-Dist: pydantic-settings>=2.0.0
Requires-Dist: pydantic>=2.0.0
Requires-Dist: pyyaml>=6.0
Requires-Dist: sqlalchemy>=2.0.0
Requires-Dist: typer[all]>=0.9.0
Provides-Extra: dev
Requires-Dist: mypy>=1.7.0; extra == 'dev'
Requires-Dist: pytest-asyncio>=0.21.0; extra == 'dev'
Requires-Dist: pytest-cov>=4.1.0; extra == 'dev'
Requires-Dist: pytest-mock>=3.12.0; extra == 'dev'
Requires-Dist: pytest>=7.4.0; extra == 'dev'
Requires-Dist: respx>=0.20.0; extra == 'dev'
Requires-Dist: ruff>=0.1.0; extra == 'dev'
Requires-Dist: types-pyyaml>=6.0.0; extra == 'dev'
